{
    "media": {
        "tv_downpath": "/media/movie/download/tv",
        "movie_downpath": "/media/movie/download/movie",
        "sortpath": "/media/movie/movie/temp",
        "moviepath": "/media/movie/movie/movie-archive",
        "tvpath": "/media/movie/movie/tv",
        "ext": ["mp4", "mkv", "avi", "m4v"],
        "log_folder": "/home/user/logs/media_organize",
        "movie_db_api": "aaaabbbbccccdddd1111222233333444",
        "min_file_size": 50000000
    },
    "emby": {
        "emby_url": "http://media.local:8096/emby",
        "emby_user_id": "aaaa1111bbbb2222cccc3333dddd4444",
        "emby_api_key": "eeee5555ffff6666gggg7777hhhh8888"
    },
    "ydl_opts": {
        "format": "bestvideo[height<=1080]+bestaudio/best[height<=1080]",
        "merge_output_format": "mkv",
        "geo_bypass": true
    }
}